<?xml version="1.0" encoding="utf-8" ?>
<dwsync>
<file name="1_0.jpg" server="studentsites.glos.ac.uk/public_html/CT4009Sem2Week11/" local="131692316450000000" remote="131692316450000000" Dst="2" />
<file name="1_1.jpg" server="studentsites.glos.ac.uk/public_html/CT4009Sem2Week11/" local="131692316450000000" remote="131692316450000000" Dst="2" />
<file name="1_2.jpg" server="studentsites.glos.ac.uk/public_html/CT4009Sem2Week11/" local="131692316450000000" remote="131692316450000000" Dst="2" />
<file name="2_0.jpg" server="studentsites.glos.ac.uk/public_html/CT4009Sem2Week11/" local="131692318400000000" remote="131692318400000000" Dst="2" />
<file name="2_1.jpg" server="studentsites.glos.ac.uk/public_html/CT4009Sem2Week11/" local="131692318400000000" remote="131692318400000000" Dst="2" />
<file name="2_2.jpg" server="studentsites.glos.ac.uk/public_html/CT4009Sem2Week11/" local="131692318400000000" remote="131692318400000000" Dst="2" />
<file name="2_3.jpg" server="studentsites.glos.ac.uk/public_html/CT4009Sem2Week11/" local="131692318400000000" remote="131692318400000000" Dst="2" />
<file name="2_4.jpg" server="studentsites.glos.ac.uk/public_html/CT4009Sem2Week11/" local="131692318400000000" remote="131692318400000000" Dst="2" />
<file name="3_0.jpg" server="studentsites.glos.ac.uk/public_html/CT4009Sem2Week11/" local="131694894640000000" remote="131694894640000000" Dst="2" />
<file name="3_1.jpg" server="studentsites.glos.ac.uk/public_html/CT4009Sem2Week11/" local="131694894640000000" remote="131694894640000000" Dst="2" />
<file name="3_2.jpg" server="studentsites.glos.ac.uk/public_html/CT4009Sem2Week11/" local="131694894640000000" remote="131694894640000000" Dst="2" />
<file name="4_0.jpg" server="studentsites.glos.ac.uk/public_html/CT4009Sem2Week11/" local="131695024080000000" remote="131695024080000000" Dst="2" />
<file name="4_1.jpg" server="studentsites.glos.ac.uk/public_html/CT4009Sem2Week11/" local="131695024080000000" remote="131695024080000000" Dst="2" />
<file name="4_2.jpg" server="studentsites.glos.ac.uk/public_html/CT4009Sem2Week11/" local="131695024080000000" remote="131695024080000000" Dst="2" />
<file name="5_0.jpg" server="studentsites.glos.ac.uk/public_html/CT4009Sem2Week11/" local="131697400700000000" remote="131697400700000000" Dst="2" />
<file name="5_1.jpg" server="studentsites.glos.ac.uk/public_html/CT4009Sem2Week11/" local="131697400700000000" remote="131697400700000000" Dst="2" />
<file name="5_2.jpg" server="studentsites.glos.ac.uk/public_html/CT4009Sem2Week11/" local="131697400700000000" remote="131697400700000000" Dst="2" />
<file name="5_3.jpg" server="studentsites.glos.ac.uk/public_html/CT4009Sem2Week11/" local="131697400700000000" remote="131697400700000000" Dst="2" />
<file name="6_0.jpg" server="studentsites.glos.ac.uk/public_html/CT4009Sem2Week11/" local="131698390160000000" remote="131698390160000000" Dst="2" />
<file name="6_1.jpg" server="studentsites.glos.ac.uk/public_html/CT4009Sem2Week11/" local="131698390160000000" remote="131698390160000000" Dst="2" />
<file name="6_2.jpg" server="studentsites.glos.ac.uk/public_html/CT4009Sem2Week11/" local="131698390160000000" remote="131698390160000000" Dst="2" />
<file name="7_0.jpg" server="studentsites.glos.ac.uk/public_html/CT4009Sem2Week11/" local="131699126930000000" remote="131699126930000000" Dst="2" />
<file name="7_1.jpg" server="studentsites.glos.ac.uk/public_html/CT4009Sem2Week11/" local="131699126930000000" remote="131699126930000000" Dst="2" />
<file name="8_0.jpg" server="studentsites.glos.ac.uk/public_html/CT4009Sem2Week11/" local="131699127390000000" remote="131699127390000000" Dst="2" />
<file name="8_1.jpg" server="studentsites.glos.ac.uk/public_html/CT4009Sem2Week11/" local="131699127390000000" remote="131699127390000000" Dst="2" />
</dwsync>